revcore_micro/__init__.py
revcore_micro/settings.py
revcore_micro/utils.py
revcore_micro/commands/__init__.py
revcore_micro/commands/init_table.py
revcore_micro/ddb/__init__.py
revcore_micro/ddb/conditions.py
revcore_micro/ddb/exceptions.py
revcore_micro/ddb/models.py
revcore_micro/flask/__init__.py
revcore_micro/flask/authorizers.py
revcore_micro/flask/exceptions.py
revcore_micro/flask/permissions.py
revcore_micro/flask/serializers.py
revcore_micro/flask/users.py
revcore_micro/flask/utils.py
revcore_micro/flask/verifiers.py
revcore_micro/jwt/__init__.py
revcore_micro/jwt/builders.py
revcore_micro-0.7.6.dist-info/METADATA
revcore_micro-0.7.6.dist-info/WHEEL
revcore_micro-0.7.6.dist-info/top_level.txt
revcore_micro-0.7.6.dist-info/RECORD
