Metadata-Version: 2.1
Name: revcore-micro
Version: 0.7.6
Summary: service core for revteltech
Home-page: UNKNOWN
Author: Chien Hsiao
Author-email: chien.hsiao@revteltech.com
License: MIT
Keywords: revteltech,micro service
Platform: UNKNOWN
Classifier: Development Status :: 3 - Alpha
Classifier: Intended Audience :: Developers
Classifier: Topic :: Software Development :: Build Tools
Classifier: License :: OSI Approved :: MIT License
Classifier: Programming Language :: Python :: 3
Classifier: Programming Language :: Python :: 3.6
Classifier: Programming Language :: Python :: 3.7
Requires-Dist: boto3
Requires-Dist: jwcrypto
Requires-Dist: marshmallow
Requires-Dist: pyjwt
